[
  {
    "q": "สิ่งแรกที่คุณสังเกตเห็นในตัวอีกคนคืออะไร?",
    "options": [
      "รอยยิ้ม",
      "พลังงาน",
      "สไตล์",
      "อารมณ์ขัน"
    ],
    "pi": 0,
    "format": "bubble"
  },
  {
    "q": "ถ้าเรามีเพลงประจำคู่ จะเป็นแนวอะไร?",
    "options": [
      "R&B / Soul",
      "Pop",
      "Indie",
      "Lo-fi Beats"
    ],
    "pi": 2,
    "format": "swipe"
  },
  {
    "q": "สิ่งที่คุณแอบชื่นชมมากที่สุดคืออะไร?",
    "options": [
      "ความมั่นใจ",
      "ความใจดี",
      "ความคิดสร้างสรรค์",
      "ความแข็งแกร่ง"
    ],
    "pi": 1,
    "format": "bubble"
  },
  {
    "q": "เลือกบรรยากาศสำหรับเดทในฝัน:",
    "options": [
      "พระอาทิตย์ตกบนดาดฟ้า",
      "ขับรถกลางคืน",
      "ดูหนังอบอุ่น",
      "ผจญภัยแบบไม่มีแผน"
    ],
    "pi": 3
  },
  {
    "q": "อธิบายความสัมพันธ์เราด้วยคำเดียว:",
    "options": [
      "วุ่นวาย",
      "อบอุ่น"
    ],
    "pi": 1,
    "format": "vs"
  },
  {
    "q": "สิ่งเล็กๆ ที่ทำให้วันดี:",
    "options": [
      "ส่งข้อความ 'คิดถึงนะ' แบบสุ่ม",
      "ทำให้หัวเราะตอนไม่คาดคิด",
      "จำรายละเอียดเล็กๆ",
      "สายตาที่มองเรา"
    ],
    "pi": 2,
    "format": "bubble"
  },
  {
    "q": "ภาษารักเปิดเต็มแม็กซ์:",
    "options": [
      "🤝 สัมผัส",
      "💬 คำพูด",
      "🛠️ การกระทำ",
      "⏳ เวลาคุณภาพ"
    ],
    "pi": 0,
    "format": "swipe"
  },
  {
    "q": "ถ้าเขาหายไปพรุ่งนี้ จะคิดถึงอะไรมากที่สุด:",
    "options": [
      "เสียงเขา",
      "การอยู่ข้างๆ",
      "มุกตลกที่ไม่มีใครเข้าใจ",
      "ความรู้สึกปลอดภัยเมื่ออยู่ด้วย"
    ],
    "pi": 3,
    "format": "bubble"
  },
  {
    "q": "พูดตรงๆ — ใครหลับก่อน?",
    "options": [
      "ฉัน ทุกครั้ง",
      "เขา ภายในไม่กี่นาที"
    ],
    "pi": 0,
    "format": "vs"
  },
  {
    "q": "พลังพิเศษของคู่เรา:",
    "options": [
      "เราสื่อสารโดยไม่ต้องพูด",
      "ทำทุกอย่างสนุก แม้แต่ซื้อของ",
      "เราสมดุลกันอย่างลงตัว",
      "เราผ่านทุกอย่างไปด้วยกันได้"
    ],
    "pi": 1
  }
]